droppy/__init__.py
droppy/_version.py
droppy/bafits.py
droppy/circularfits.py
droppy/common.py
droppy/droppy.py
droppy/edgedetection.py
droppy/imageanalysis.py
droppy/linearfits.py
droppy/moviehandling.py
droppy-1.0.0.dev2.dist-info/LICENSE
droppy-1.0.0.dev2.dist-info/METADATA
droppy-1.0.0.dev2.dist-info/WHEEL
droppy-1.0.0.dev2.dist-info/entry_points.txt
droppy-1.0.0.dev2.dist-info/top_level.txt
droppy-1.0.0.dev2.dist-info/RECORD
