Metadata-Version: 2.1
Name: droppy
Version: 1.0.0.dev2
Summary: # Python contact angle image processing analysis
Home-page: https://github.com/michaelorella/contactangles
Author: Michael J. Orella
Author-email: morella@mit.edu
License: MIT
Platform: UNKNOWN
Requires-Python: >3.6
Requires-Dist: numpy
Requires-Dist: scipy
Requires-Dist: scikit-image
Requires-Dist: imageio
Requires-Dist: matplotlib
Requires-Dist: imageio-ffmpeg
Requires-Dist: pyqt5
Requires-Dist: numba
Requires-Dist: joblib
